TREEplus/TREEplus.py
TREEplus/__init__.py
TREEplus/setup.py
TREEplus-project/TREEplus.py
TREEplus-project/__init__.py
TREEplus-project/setup.py
TREEplus2/TREEplus.py
TREEplus2/__init__.py
TREEplus2/setup.py
TREEplus_project-0.1.dist-info/METADATA
TREEplus_project-0.1.dist-info/WHEEL
TREEplus_project-0.1.dist-info/top_level.txt
TREEplus_project-0.1.dist-info/RECORD
