Metadata-Version: 2.1
Name: TREEplus-project
Version: 0.1
Summary: Standard and Non-Standard Tree Based Methods
Author: Daniel Fynn
Author-email: <df390@uowmail.edu.au>
Keywords: python,tree,CART
Classifier: Development Status :: 3 - Alpha
Classifier: Intended Audience :: Education
Classifier: Programming Language :: Python :: 2
Classifier: Programming Language :: Python :: 3
Classifier: Operating System :: MacOS :: MacOS X
Classifier: Operating System :: Microsoft :: Windows
